emotional-0.6.0.dist-info/METADATA
emotional-0.6.0.dist-info/WHEEL
emotional-0.6.0.dist-info/entry_points.txt
emotional-0.6.0.dist-info/licenses/LICENSE
emotional/VERSION
emotional/__init__.py
emotional/config.py
emotional/defaults.py
emotional/github.py
emotional/gitlab.py
emotional/jira.py
emotional/plugin.py
emotional/templates/CHANGELOG.md.j2
emotional/templates/example.jinja
emotional/templates/info.md.jinja
emotional/templates/macros.md.jinja
emotional/utils.py
emotional-0.6.0.dist-info/RECORD
