Metadata-Version: 2.1
Name: emotional
Version: 0.6.0
Summary: A Commitizen plugin for conventional commit with emojis and integrations
Author-Email: "Axel H." <noirbizarre@gmail.com>
License: MIT
Project-URL: Homepage, https://github.com/noirbizarre/emotional
Project-URL: Repository, https://github.com/noirbizarre/emotional
Project-URL: Issues, https://github.com/noirbizarre/emotional/issues
Requires-Python: >=3.10
Requires-Dist: commitizen>=4.0
